[{"line":1,"uri":"file:src/test/resources/features/login.feature","id":"login","keyword":"Feature","name":"Login","description":"","elements":[{"start_timestamp":"2026-02-12T18:39:46.087Z","line":26,"id":"login;login-with-correct-email-and-wrong-password;;2","type":"scenario","keyword":"Scenario Outline","name":"Login with correct email and wrong password","description":"","steps":[{"keyword":"Given ","line":15,"match":{"location":"com.ilcarro.stepDefinitions.HomePageSteps.launch_Chrome_browser()"},"name":"User launches Chrome browser","result":{"duration":2129436000,"status":"passed"}},{"keyword":"When ","line":16,"match":{"location":"com.ilcarro.stepDefinitions.HomePageSteps.open_ilcarro_HomePage()"},"name":"User opens ilcarro HomePage","result":{"duration":719965000,"status":"passed"}},{"keyword":"And ","line":17,"match":{"location":"com.ilcarro.stepDefinitions.LoginSteps.click_on_Login_link()"},"name":"User clicks on Login link","result":{"duration":2208572000,"status":"passed"}},{"keyword":"And ","line":18,"match":{"location":"com.ilcarro.stepDefinitions.LoginSteps.enter_wrong_password(io.cucumber.datatable.DataTable)"},"name":"User enters correct email and wrong password","result":{"duration":253217000,"status":"passed"},"rows":[{"cells":["email","password"]},{"cells":["manuel@gm.com","Manuel12341"]}]},{"keyword":"And ","line":21,"match":{"location":"com.ilcarro.stepDefinitions.LoginSteps.clicks_on_Yalla()"},"name":"User clicks on Yalla button","result":{"duration":46559000,"status":"passed"}},{"keyword":"Then ","line":22,"match":{"location":"com.ilcarro.stepDefinitions.LoginSteps.verify_Error()"},"name":"User verifies Error message is displayed","result":{"duration":1475548000,"status":"passed"}},{"keyword":"And ","line":23,"match":{"location":"com.ilcarro.stepDefinitions.HomePageSteps.quit_browser()"},"name":"User quites browser","result":{"duration":101561000,"status":"passed"}}],"tags":[{"name":"@wrongPassword"}]},{"start_timestamp":"2026-02-12T18:39:53.036Z","line":27,"id":"login;login-with-correct-email-and-wrong-password;;3","type":"scenario","keyword":"Scenario Outline","name":"Login with correct email and wrong password","description":"","steps":[{"keyword":"Given ","line":15,"match":{"location":"com.ilcarro.stepDefinitions.HomePageSteps.launch_Chrome_browser()"},"name":"User launches Chrome browser","result":{"duration":1073209000,"status":"passed"}},{"keyword":"When ","line":16,"match":{"location":"com.ilcarro.stepDefinitions.HomePageSteps.open_ilcarro_HomePage()"},"name":"User opens ilcarro HomePage","result":{"duration":713159000,"status":"passed"}},{"keyword":"And ","line":17,"match":{"location":"com.ilcarro.stepDefinitions.LoginSteps.click_on_Login_link()"},"name":"User clicks on Login link","result":{"duration":2532970000,"status":"passed"}},{"keyword":"And ","line":18,"match":{"location":"com.ilcarro.stepDefinitions.LoginSteps.enter_wrong_password(io.cucumber.datatable.DataTable)"},"name":"User enters correct email and wrong password","result":{"duration":180155000,"status":"passed"},"rows":[{"cells":["email","password"]},{"cells":["manuel@gm.com","manuel1234!"]}]},{"keyword":"And ","line":21,"match":{"location":"com.ilcarro.stepDefinitions.LoginSteps.clicks_on_Yalla()"},"name":"User clicks on Yalla button","result":{"duration":38646000,"status":"passed"}},{"keyword":"Then ","line":22,"match":{"location":"com.ilcarro.stepDefinitions.LoginSteps.verify_Error()"},"name":"User verifies Error message is displayed","result":{"duration":1948664000,"status":"passed"}},{"keyword":"And ","line":23,"match":{"location":"com.ilcarro.stepDefinitions.HomePageSteps.quit_browser()"},"name":"User quites browser","result":{"duration":92603000,"status":"passed"}}],"tags":[{"name":"@wrongPassword"}]},{"start_timestamp":"2026-02-12T18:39:59.619Z","line":28,"id":"login;login-with-correct-email-and-wrong-password;;4","type":"scenario","keyword":"Scenario Outline","name":"Login with correct email and wrong password","description":"","steps":[{"keyword":"Given ","line":15,"match":{"location":"com.ilcarro.stepDefinitions.HomePageSteps.launch_Chrome_browser()"},"name":"User launches Chrome browser","result":{"duration":976666000,"status":"passed"}},{"keyword":"When ","line":16,"match":{"location":"com.ilcarro.stepDefinitions.HomePageSteps.open_ilcarro_HomePage()"},"name":"User opens ilcarro HomePage","result":{"duration":680029000,"status":"passed"}},{"keyword":"And ","line":17,"match":{"location":"com.ilcarro.stepDefinitions.LoginSteps.click_on_Login_link()"},"name":"User clicks on Login link","result":{"duration":1776236000,"status":"passed"}},{"keyword":"And ","line":18,"match":{"location":"com.ilcarro.stepDefinitions.LoginSteps.enter_wrong_password(io.cucumber.datatable.DataTable)"},"name":"User enters correct email and wrong password","result":{"duration":199588000,"status":"passed"},"rows":[{"cells":["email","password"]},{"cells":["manuel@gm.com","MANUEL1234!"]}]},{"keyword":"And ","line":21,"match":{"location":"com.ilcarro.stepDefinitions.LoginSteps.clicks_on_Yalla()"},"name":"User clicks on Yalla button","result":{"duration":35525000,"status":"passed"}},{"keyword":"Then ","line":22,"match":{"location":"com.ilcarro.stepDefinitions.LoginSteps.verify_Error()"},"name":"User verifies Error message is displayed","result":{"duration":1980471000,"status":"passed"}},{"keyword":"And ","line":23,"match":{"location":"com.ilcarro.stepDefinitions.HomePageSteps.quit_browser()"},"name":"User quites browser","result":{"duration":87548000,"status":"passed"}}],"tags":[{"name":"@wrongPassword"}]},{"start_timestamp":"2026-02-12T18:40:05.358Z","line":29,"id":"login;login-with-correct-email-and-wrong-password;;5","type":"scenario","keyword":"Scenario Outline","name":"Login with correct email and wrong password","description":"","steps":[{"keyword":"Given ","line":15,"match":{"location":"com.ilcarro.stepDefinitions.HomePageSteps.launch_Chrome_browser()"},"name":"User launches Chrome browser","result":{"duration":997755000,"status":"passed"}},{"keyword":"When ","line":16,"match":{"location":"com.ilcarro.stepDefinitions.HomePageSteps.open_ilcarro_HomePage()"},"name":"User opens ilcarro HomePage","result":{"duration":2631564000,"status":"passed"}},{"keyword":"And ","line":17,"match":{"location":"com.ilcarro.stepDefinitions.LoginSteps.click_on_Login_link()"},"name":"User clicks on Login link","result":{"duration":54933000,"status":"passed"}},{"keyword":"And ","line":18,"match":{"location":"com.ilcarro.stepDefinitions.LoginSteps.enter_wrong_password(io.cucumber.datatable.DataTable)"},"name":"User enters correct email and wrong password","result":{"duration":180656000,"status":"passed"},"rows":[{"cells":["email","password"]},{"cells":["manuel@gm.com","Ьфтгуд1234!"]}]},{"keyword":"And ","line":21,"match":{"location":"com.ilcarro.stepDefinitions.LoginSteps.clicks_on_Yalla()"},"name":"User clicks on Yalla button","result":{"duration":35207000,"status":"passed"}},{"keyword":"Then ","line":22,"match":{"location":"com.ilcarro.stepDefinitions.LoginSteps.verify_Error()"},"name":"User verifies Error message is displayed","result":{"duration":1423712000,"status":"passed"}},{"keyword":"And ","line":23,"match":{"location":"com.ilcarro.stepDefinitions.HomePageSteps.quit_browser()"},"name":"User quites browser","result":{"duration":92147000,"status":"passed"}}],"tags":[{"name":"@wrongPassword"}]}],"tags":[]},{"line":1,"uri":"file:src/test/resources/features/navigate.feature","id":"homepage","keyword":"Feature","name":"HomePage","description":"","elements":[{"start_timestamp":"2026-02-12T18:40:10.779Z","line":4,"id":"homepage;verify-homepage-title-is-displayed","type":"scenario","keyword":"Scenario","name":"Verify HomePage title is displayed","description":"","steps":[{"keyword":"Given ","line":5,"match":{"location":"com.ilcarro.stepDefinitions.HomePageSteps.launch_Chrome_browser()"},"name":"User launches Chrome browser","result":{"duration":991839000,"status":"passed"}},{"keyword":"When ","line":6,"match":{"location":"com.ilcarro.stepDefinitions.HomePageSteps.open_ilcarro_HomePage()"},"name":"User opens ilcarro HomePage","result":{"duration":677579000,"status":"passed"}},{"keyword":"Then ","line":7,"match":{"location":"com.ilcarro.stepDefinitions.HomePageSteps.verify_HomePage_title()"},"name":"User verifies HomePage title is displayed","result":{"duration":2009181000,"status":"passed"}},{"keyword":"And ","line":8,"match":{"location":"com.ilcarro.stepDefinitions.HomePageSteps.quit_browser()"},"name":"User quites browser","result":{"duration":94492000,"status":"passed"}}],"tags":[{"name":"@navigate"}]}],"tags":[]}]